qtest/__init__.py
qtest/qtest.py
qasymphony_qtest_library-0.2.2.dist-info/LICENSE
qasymphony_qtest_library-0.2.2.dist-info/METADATA
qasymphony_qtest_library-0.2.2.dist-info/WHEEL
qasymphony_qtest_library-0.2.2.dist-info/top_level.txt
qasymphony_qtest_library-0.2.2.dist-info/RECORD
