Metadata-Version: 2.1
Name: qasymphony-qtest-library
Version: 0.2.2
Summary: UNKNOWN
Home-page: https://github.com/paul-nelson-baker/python-qtest-library
Author: Paul N. Baker
Author-email: paul.nelson.baker@gmail.com
License: ISC
Keywords: qasymphony qtest quality-assurance qa
Platform: UNKNOWN
Classifier: Development Status :: 3 - Alpha
Classifier: Intended Audience :: Developers
Classifier: Programming Language :: Python :: 3.6
Requires-Python: ~=3.6
License-File: LICENSE
Requires-Dist: requests (>=2.18.4)
